<?xml version='1.0'?>

<GLExtension name="GL_EXT_coordinate_frame">
	<Tokens>
		<Token name="GL_TANGENT_ARRAY_EXT" value="0x8439"/>
		<Token name="GL_BINORMAL_ARRAY_EXT" value="0x843A"/>
		<Token name="GL_CURRENT_TANGENT_EXT" value="0x843B"/>
		<Token name="GL_CURRENT_BINORMAL_EXT" value="0x843C"/>
		<Token name="GL_TANGENT_ARRAY_TYPE_EXT" value="0x843E"/>
		<Token name="GL_TANGENT_ARRAY_STRIDE_EXT" value="0x843F"/>
		<Token name="GL_BINORMAL_ARRAY_TYPE_EXT" value="0x8440"/>
		<Token name="GL_BINORMAL_ARRAY_STRIDE_EXT" value="0x8441"/>
		<Token name="GL_TANGENT_ARRAY_POINTER_EXT" value="0x8442"/>
		<Token name="GL_BINORMAL_ARRAY_POINTER_EXT" value="0x8443"/>
		<Token name="GL_MAP1_TANGENT_EXT" value="0x8444"/>
		<Token name="GL_MAP2_TANGENT_EXT" value="0x8445"/>
		<Token name="GL_MAP1_BINORMAL_EXT" value="0x8446"/>
		<Token name="GL_MAP2_BINORMAL_EXT" value="0x8447"/>
	</Tokens>

	<Functions>
		<Function name="glTangent3bEXT" return="void">
			<Param type="GLbyte" name="tx"/>
			<Param type="GLbyte" name="ty"/>
			<Param type="GLbyte" name="tz"/>
		</Function>
		<Function name="glTangent3bvEXT" return="void">
			<Param type="const GLbyte*" name="v"/>
		</Function>
		<Function name="glTangent3dEXT" return="void">
			<Param type="GLdouble" name="tx"/>
			<Param type="GLdouble" name="ty"/>
			<Param type="GLdouble" name="tz"/>
		</Function>
		<Function name="glTangent3dvEXT" return="void">
			<Param type="const GLdouble*" name="v"/>
		</Function>
		<Function name="glTangent3fEXT" return="void" params="GLfloat tx, GLfloat ty, GLfloat tz">
			<Param type="GLfloat" name="tx"/>
			<Param type="GLfloat" name="ty"/>
			<Param type="GLfloat" name="tz"/>
		</Function>
		<Function name="glTangent3fvEXT" return="void">
			<Param type="const GLfloat*" name="v"/>
		</Function>
		<Function name="glTangent3iEXT" return="void">
			<Param type="GLint" name="tx"/>
			<Param type="GLint" name="ty"/>
			<Param type="GLint" name="tz"/>
		</Function>
		<Function name="glTangent3ivEXT" return="void">
			<Param type="const GLint*" name="v"/>
		</Function>
		<Function name="glTangent3sEXT" return="void">
			<Param type="GLshort" name="tx"/>
			<Param type="GLshort" name="ty"/>
			<Param type="GLshort" name="tz"/>
		</Function>
		<Function name="glTangent3svEXT" return="void">
			<Param type="const GLshort*" name="v"/>
		</Function>
		<Function name="glBinormal3bEXT" return="void">
			<Param type="GLbyte" name="bx"/>
			<Param type="GLbyte" name="by"/>
			<Param type="GLbyte" name="bz"/>
		</Function>
		<Function name="glBinormal3bvEXT" return="void">
			<Param type="const GLbyte*" name="v"/>
		</Function>
		<Function name="glBinormal3dEXT" return="void">
			<Param type="GLdouble" name="bx"/>
			<Param type="GLdouble" name="by"/>
			<Param type="GLdouble" name="bz"/>
		</Function>
		<Function name="glBinormal3dvEXT" return="void">
			<Param type="const GLdouble*" name="v"/>
		</Function>
		<Function name="glBinormal3fEXT" return="void">
			<Param type="GLfloat" name="bx"/>
			<Param type="GLfloat" name="by"/>
			<Param type="GLfloat" name="bz"/>
		</Function>
		<Function name="glBinormal3fvEXT" return="void">
			<Param type="const GLfloat*" name="v"/>
		</Function>
		<Function name="glBinormal3iEXT" return="void">
			<Param type="GLint" name="bx"/>
			<Param type="GLint" name="by"/>
			<Param type="GLint" name="bz"/>
		</Function>
		<Function name="glBinormal3ivEXT" return="void">
			<Param type="const GLint*" name="v"/>
		</Function>
		<Function name="glBinormal3sEXT" return="void">
			<Param type="GLshort" name="bx"/>
			<Param type="GLshort" name="by"/>
			<Param type="GLshort" name="bz"/>
		</Function>
		<Function name="glBinormal3svEXT" return="void">
			<Param type="const GLshort*" name="v"/>
		</Function>
		<Function name="glTangentPointerEXT" return="void">
			<Param type="GLenum" name="type"/>
			<Param type="GLsizei" name="stride"/>
			<Param type="const GLvoid*" name="pointer"/>
		</Function>
		<Function name="glBinormalPointerEXT" return="void">
			<Param type="GLenum" name="type"/>
			<Param type="GLsizei" name="stride"/>
			<Param type="const GLvoid*" name="pointer"/>
		</Function>
	</Functions>

	<Vendors>
		<Vendor name="GL_EXT" string="GL_EXT_coordinate_frame">
			<Name name="glTangent3bEXT"/>
			<Name name="glTangent3bvEXT"/>
			<Name name="glTangent3dEXT"/>
			<Name name="glTangent3dvEXT"/>
			<Name name="glTangent3fEXT"/>
			<Name name="glTangent3fvEXT"/>
			<Name name="glTangent3iEXT"/>
			<Name name="glTangent3ivEXT"/>
			<Name name="glTangent3sEXT"/>
			<Name name="glTangent3svEXT"/>
			<Name name="glBinormal3bEXT"/>
			<Name name="glBinormal3bvEXT"/>
			<Name name="glBinormal3dEXT"/>
			<Name name="glBinormal3dvEXT"/>
			<Name name="glBinormal3fEXT"/>
			<Name name="glBinormal3fvEXT"/>
			<Name name="glBinormal3iEXT"/>
			<Name name="glBinormal3ivEXT"/>
			<Name name="glBinormal3sEXT"/>
			<Name name="glBinormal3svEXT"/>
			<Name name="glTangentPointerEXT"/>
			<Name name="glBinormalPointerEXT"/>
		</Vendor>
	</Vendors>

	<InitPath>
		<Init name="GL_EXT"/>
	</InitPath>
</GLExtension>
